<?xml version="1.0" encoding="utf-8"?>
<Defs>



	<!-- Nuclear Survivor -->
	<PawnKindDef>
		<defName>NuclearSurvivorGhoul</defName>
		<label>Researchers</label>
		<race>VaulTecGhoul</race>
		<defaultFactionType>PlayerColony</defaultFactionType>
		<chemicalAddictionChance>0.06</chemicalAddictionChance>
		<maxGenerationAge>42</maxGenerationAge>
		<combatPower>80</combatPower>
		<isFighter>false</isFighter>
		<apparelIgnorePollution MayRequire="Ludeon.RimWorld.Biotech">true</apparelIgnorePollution>
		<minGenerationAge>18</minGenerationAge>
		<techHediffsChance>0.05</techHediffsChance>
		<techHediffsMoney>50~1800</techHediffsMoney>
		<initialWillRange>0~0</initialWillRange>
		<humanPregnancyChance>0.006</humanPregnancyChance>
		<techHediffsTags>
		    <li>Ghoul</li>
			<li>Poor</li>
			<li>Simple</li>
			<li>ImplantEmpireCommon</li>
		</techHediffsTags>
		<apparelMoney>
			<min>4000</min>
			<max>5500</max>
		</apparelMoney>
		<apparelTags>
			<li>BrotherhoodLight</li>
			<li>BrotherhoodMedium</li>
		</apparelTags>
		<weaponMoney>
			<min>1300</min>
			<max>2500</max>
		</weaponMoney>
		<weaponTags>
			<li>RF3</li>
		</weaponTags>
		<apparelRequired>
		  <li>Jaffa_BasicHelmet</li>
			<li>CE_Apparel_TacVest</li>
			<li>Apparello_PipBoy</li>
		</apparelRequired>
		<apparelIgnoreSeasons>true</apparelIgnoreSeasons>
		<backstoryCryptosleepCommonality>1</backstoryCryptosleepCommonality>
		<forceNormalGearQuality>true</forceNormalGearQuality>
		<techHediffsDisallowTags>
			<li>PainCauser</li>
		</techHediffsDisallowTags>
		<initialResistanceRange>9~18</initialResistanceRange>
		<xenotypeSet Inherit="False">
		  <xenotypeChances>
			<OE_Ghoul MayRequire="Ludeon.RimWorld.Biotech">999</OE_Ghoul>
		  </xenotypeChances>
		</xenotypeSet>
		<modExtensions>
			<li Class="CombatExtended.LoadoutPropertiesExtension">
				<primaryMagazineCount>
					<min>13</min>
					<max>15</max>
				</primaryMagazineCount>
				<sidearms>
					<li>
						<generateChance>0.3</generateChance>
						<sidearmMoney>
							<min>250</min>
							<max>350</max>
						</sidearmMoney>
						<weaponTags>
							<li>GrenadeTierTwo</li>
						</weaponTags>
						<magazineCount>
							<min>1</min>
							<max>3</max>
						</magazineCount>
					</li>
					<li>
						<generateChance>0.1</generateChance>
						<sidearmMoney>
							<min>50</min>
							<max>150</max>
						</sidearmMoney>
						<weaponTags>
							<li>GrenadeFlashbang</li>
						</weaponTags>
						<magazineCount>
							<min>1</min>
							<max>2</max>
						</magazineCount>
					</li>
				</sidearms>
			</li>
		</modExtensions>
	</PawnKindDef>

</Defs>